<?xml version="1.0"?>
<ZopeData>
  <record id="1" aka="AAAAAAAAAAE=">
    <pickle>
      <global name="Notification Message" module="erp5.portal_type"/>
    </pickle>
    <pickle>
      <dictionary>
        <item>
            <key> <string>_Access_contents_information_Permission</string> </key>
            <value>
              <tuple>
                <string>Assignee</string>
                <string>Assignor</string>
                <string>Associate</string>
                <string>Manager</string>
                <string>Owner</string>
              </tuple>
            </value>
        </item>
        <item>
            <key> <string>_Add_portal_content_Permission</string> </key>
            <value>
              <tuple>
                <string>Assignee</string>
                <string>Assignor</string>
                <string>Manager</string>
                <string>Owner</string>
              </tuple>
            </value>
        </item>
        <item>
            <key> <string>_Delete_objects_Permission</string> </key>
            <value>
              <tuple>
                <string>Assignee</string>
                <string>Assignor</string>
                <string>Manager</string>
                <string>Owner</string>
              </tuple>
            </value>
        </item>
        <item>
            <key> <string>_Modify_portal_content_Permission</string> </key>
            <value>
              <tuple>
                <string>Assignee</string>
                <string>Assignor</string>
                <string>Manager</string>
                <string>Owner</string>
              </tuple>
            </value>
        </item>
        <item>
            <key> <string>_View_Permission</string> </key>
            <value>
              <tuple>
                <string>Assignee</string>
                <string>Assignor</string>
                <string>Associate</string>
                <string>Manager</string>
                <string>Owner</string>
              </tuple>
            </value>
        </item>
        <item>
            <key> <string>default_reference</string> </key>
            <value> <string>vifib.fiber-request.accept</string> </value>
        </item>
        <item>
            <key> <string>description</string> </key>
            <value> <string>Message envoyé après avoir reçu le dossier et accepté la demande</string> </value>
        </item>
        <item>
            <key> <string>id</string> </key>
            <value> <string>vifib_fiber_request_accept</string> </value>
        </item>
        <item>
            <key> <string>language</string> </key>
            <value> <string>fr</string> </value>
        </item>
        <item>
            <key> <string>portal_type</string> </key>
            <value> <string>Notification Message</string> </value>
        </item>
        <item>
            <key> <string>text_content</string> </key>
            <value> <string>Bonjour ${customer_name},\r\n
\r\n
Nous avons bien reçu votre dossier d\'inscription et venons de la valider.\r\n
\r\n
Nous allons vous contacter très prochainement par téléphone pour prendre rendez vous pour l\'installation des serveurs.\r\n
\r\n
Cordialement,\r\n
L\'équipe de Vifib</string> </value>
        </item>
        <item>
            <key> <string>text_content_substitution_mapping_method_id</string> </key>
            <value> <string>NotificationMessage_getSubstitutionMappingDictFromArgument</string> </value>
        </item>
        <item>
            <key> <string>text_format</string> </key>
            <value> <string>text/plain</string> </value>
        </item>
        <item>
            <key> <string>title</string> </key>
            <value> <string>VIFIB : Votre demande est accepté</string> </value>
        </item>
        <item>
            <key> <string>version</string> </key>
            <value> <string>0.1</string> </value>
        </item>
      </dictionary>
    </pickle>
  </record>
</ZopeData>
